[{"createdAt":"2026-04-13T21:52:51Z","version":"0.6.14","distributions":[{"filename":"Aurox-0.6.14-rh8_0-any.yak","platform":"any","rhinoVersion":"rh8_0","url":"https://files.mcneel.com/yak/packages/Aurox-0.6.14-rh8_0-any.yak"},{"filename":"Aurox-0.6.14-rh7_13-any.yak","platform":"any","rhinoVersion":"rh7_13","url":"https://files.mcneel.com/yak/packages/Aurox-0.6.14-rh7_13-any.yak"}],"prerelease":false},{"createdAt":"2026-04-13T20:29:25Z","version":"0.6.13","distributions":[{"filename":"Aurox-0.6.13-rh8_0-any.yak","platform":"any","rhinoVersion":"rh8_0","url":"https://files.mcneel.com/yak/packages/Aurox-0.6.13-rh8_0-any.yak"},{"filename":"Aurox-0.6.13-rh7_13-any.yak","platform":"any","rhinoVersion":"rh7_13","url":"https://files.mcneel.com/yak/packages/Aurox-0.6.13-rh7_13-any.yak"}],"prerelease":false},{"createdAt":"2026-04-13T20:29:25Z","version":"0.6.12","distributions":[{"filename":"Aurox-0.6.12-rh8_0-any.yak","platform":"any","rhinoVersion":"rh8_0","url":"https://files.mcneel.com/yak/packages/Aurox-0.6.12-rh8_0-any.yak"},{"filename":"Aurox-0.6.12-rh7_13-any.yak","platform":"any","rhinoVersion":"rh7_13","url":"https://files.mcneel.com/yak/packages/Aurox-0.6.12-rh7_13-any.yak"}],"prerelease":false},{"createdAt":"2026-04-13T20:29:25Z","version":"0.6.11","distributions":[{"filename":"Aurox-0.6.11-rh8_0-any.yak","platform":"any","rhinoVersion":"rh8_0","url":"https://files.mcneel.com/yak/packages/Aurox-0.6.11-rh8_0-any.yak"},{"filename":"Aurox-0.6.11-rh7_38-any.yak","platform":"any","rhinoVersion":"rh7_38","url":"https://files.mcneel.com/yak/packages/Aurox-0.6.11-rh7_38-any.yak"}],"prerelease":false},{"createdAt":"2026-04-13T21:06:54Z","version":"0.6.10","distributions":[{"filename":"Aurox-0.6.10-rh8_0-any.yak","platform":"any","rhinoVersion":"rh8_0","url":"https://files.mcneel.com/yak/packages/Aurox-0.6.10-rh8_0-any.yak"},{"filename":"Aurox-0.6.10-rh7_38-any.yak","platform":"any","rhinoVersion":"rh7_38","url":"https://files.mcneel.com/yak/packages/Aurox-0.6.10-rh7_38-any.yak"}],"prerelease":false},{"createdAt":"2026-04-12T20:24:10Z","version":"0.6.9","distributions":[{"filename":"Aurox-0.6.9-rh8_0-any.yak","platform":"any","rhinoVersion":"rh8_0","url":"https://files.mcneel.com/yak/packages/Aurox-0.6.9-rh8_0-any.yak"},{"filename":"Aurox-0.6.9-rh7_38-any.yak","platform":"any","rhinoVersion":"rh7_38","url":"https://files.mcneel.com/yak/packages/Aurox-0.6.9-rh7_38-any.yak"}],"prerelease":false},{"createdAt":"2026-04-12T20:19:08Z","version":"0.6.8","distributions":[{"filename":"Aurox-0.6.8-rh7_38-any.yak","platform":"any","rhinoVersion":"rh7_38","url":"https://files.mcneel.com/yak/packages/Aurox-0.6.8-rh7_38-any.yak"},{"filename":"Aurox-0.6.8-any-any.yak","platform":"any","rhinoVersion":"any","url":"https://files.mcneel.com/yak/packages/Aurox-0.6.8-any-any.yak"}],"prerelease":false},{"createdAt":"2026-04-11T20:21:13Z","version":"0.6.7","distributions":[{"filename":"Aurox-0.6.7-rh8_0-any.yak","platform":"any","rhinoVersion":"rh8_0","url":"https://files.mcneel.com/yak/packages/Aurox-0.6.7-rh8_0-any.yak"},{"filename":"Aurox-0.6.7-rh7_38-any.yak","platform":"any","rhinoVersion":"rh7_38","url":"https://files.mcneel.com/yak/packages/Aurox-0.6.7-rh7_38-any.yak"}],"prerelease":false}]