[{"createdAt":"2022-08-12T12:30:36Z","version":"1.0.2","distributions":[{"filename":"Examples-1.0.2-rh7_0-win.yak","platform":"win","rhinoVersion":"rh7_0","url":"https://files.mcneel.com/yak/packages/Examples-1.0.2-rh7_0-win.yak","createdAt":"2022-08-12T12:30:37Z"},{"filename":"Examples-1.0.2-rh6_0-win.yak","platform":"win","rhinoVersion":"rh6_0","url":"https://files.mcneel.com/yak/packages/Examples-1.0.2-rh6_0-win.yak","createdAt":"2022-08-12T12:30:36Z"}],"prerelease":false,"downloadCount":763,"downloads":{"lastDay":1,"lastWeek":2,"lastMonth":12}},{"createdAt":"2022-08-11T03:55:09Z","version":"1.0.1","distributions":[{"filename":"Examples-1.0.1-rh7_0-win.yak","platform":"win","rhinoVersion":"rh7_0","url":"https://files.mcneel.com/yak/packages/Examples-1.0.1-rh7_0-win.yak","createdAt":"2022-08-11T03:55:10Z"},{"filename":"Examples-1.0.1-rh6_0-win.yak","platform":"win","rhinoVersion":"rh6_0","url":"https://files.mcneel.com/yak/packages/Examples-1.0.1-rh6_0-win.yak","createdAt":"2022-08-11T03:55:09Z"}],"prerelease":false,"downloadCount":19,"downloads":{"lastDay":0,"lastWeek":0,"lastMonth":0}},{"createdAt":"2022-08-09T10:25:02Z","version":"1.0.0","distributions":[{"filename":"Examples-1.0.0-rh7_0-win.yak","platform":"win","rhinoVersion":"rh7_0","url":"https://files.mcneel.com/yak/packages/Examples-1.0.0-rh7_0-win.yak","createdAt":"2022-08-09T10:25:03Z"},{"filename":"Examples-1.0.0-rh6_0-win.yak","platform":"win","rhinoVersion":"rh6_0","url":"https://files.mcneel.com/yak/packages/Examples-1.0.0-rh6_0-win.yak","createdAt":"2022-08-09T10:25:02Z"}],"prerelease":false,"downloadCount":14,"downloads":{"lastDay":0,"lastWeek":0,"lastMonth":0}}]