[{"createdAt":"2022-05-17T20:56:37Z","version":"1.2.2","distributions":[{"filename":"Mallard-1.2.2-rh7_12-win.yak","platform":"win","rhinoVersion":"rh7_12","url":"https://files.mcneel.com/yak/packages/Mallard-1.2.2-rh7_12-win.yak","createdAt":"2022-05-17T20:56:37Z"},{"filename":"Mallard-1.2.2-rh7_0-win.yak","platform":"win","rhinoVersion":"rh7_0","url":"https://files.mcneel.com/yak/packages/Mallard-1.2.2-rh7_0-win.yak","createdAt":"2022-05-17T21:07:04Z"}],"prerelease":false,"downloadCount":192,"downloads":{"lastDay":0,"lastWeek":0,"lastMonth":2}},{"createdAt":"2021-12-21T22:52:55Z","version":"1.2.1","distributions":[{"filename":"Mallard-1.2.1-rh7_12-win.yak","platform":"win","rhinoVersion":"rh7_12","url":"https://files.mcneel.com/yak/packages/Mallard-1.2.1-rh7_12-win.yak","createdAt":"2022-05-17T20:43:40Z"},{"filename":"Mallard-1.2.1-rh7_12-any.yak","platform":"any","rhinoVersion":"rh7_12","url":"https://files.mcneel.com/yak/packages/Mallard-1.2.1-rh7_12-any.yak","createdAt":"2021-12-21T22:52:55Z"}],"prerelease":false,"downloadCount":97,"downloads":{"lastDay":0,"lastWeek":0,"lastMonth":0}}]