[{"createdAt":"2022-01-09T01:42:13Z","version":"1.0.2","distributions":[{"filename":"stgRivets-1.0.2-rh7_0-any.yak","platform":"any","rhinoVersion":"rh7_0","url":"https://files.mcneel.com/yak/packages/stgRivets-1.0.2-rh7_0-any.yak","createdAt":"2022-01-17T15:49:58Z"},{"filename":"stgRivets-1.0.2-rh6_0-any.yak","platform":"any","rhinoVersion":"rh6_0","url":"https://files.mcneel.com/yak/packages/stgRivets-1.0.2-rh6_0-any.yak","createdAt":"2022-01-09T01:42:13Z"}],"prerelease":false,"downloadCount":353,"downloads":{"lastDay":0,"lastWeek":2,"lastMonth":18}}]