[{"createdAt":"2025-02-22T16:26:47Z","version":"0.5.0","distributions":[{"filename":"Synapse-0.5.0-rh8_0-any.yak","platform":"any","rhinoVersion":"rh8_0","url":"https://files.mcneel.com/yak/packages/Synapse-0.5.0-rh8_0-any.yak"},{"filename":"Synapse-0.5.0-rh7_0-any.yak","platform":"any","rhinoVersion":"rh7_0","url":"https://files.mcneel.com/yak/packages/Synapse-0.5.0-rh7_0-any.yak"}],"prerelease":false},{"createdAt":"2021-08-06T00:56:09Z","version":"0.4.0","distributions":[{"filename":"Synapse-0.4.0-rh7_0-any.yak","platform":"any","rhinoVersion":"rh7_0","url":"https://files.mcneel.com/yak/packages/Synapse-0.4.0-rh7_0-any.yak"},{"filename":"Synapse-0.4.0-rh6_34-any.yak","platform":"any","rhinoVersion":"rh6_34","url":"https://files.mcneel.com/yak/packages/Synapse-0.4.0-rh6_34-any.yak"}],"prerelease":false},{"createdAt":"2021-07-17T18:10:17Z","version":"0.3.1","distributions":[{"filename":"Synapse-0.3.1-rh7_0-any.yak","platform":"any","rhinoVersion":"rh7_0","url":"https://files.mcneel.com/yak/packages/Synapse-0.3.1-rh7_0-any.yak"},{"filename":"Synapse-0.3.1-rh6_34-any.yak","platform":"any","rhinoVersion":"rh6_34","url":"https://files.mcneel.com/yak/packages/Synapse-0.3.1-rh6_34-any.yak"}],"prerelease":false},{"createdAt":"2021-03-27T17:43:37Z","version":"0.3.0","distributions":[{"filename":"Synapse-0.3.0-rh7_0-any.yak","platform":"any","rhinoVersion":"rh7_0","url":"https://files.mcneel.com/yak/packages/Synapse-0.3.0-rh7_0-any.yak"},{"filename":"Synapse-0.3.0-rh6_34-any.yak","platform":"any","rhinoVersion":"rh6_34","url":"https://files.mcneel.com/yak/packages/Synapse-0.3.0-rh6_34-any.yak"}],"prerelease":false},{"createdAt":"2021-03-07T21:17:19Z","version":"0.2.0","distributions":[{"filename":"Synapse-0.2.0-rh7_0-any.yak","platform":"any","rhinoVersion":"rh7_0","url":"https://files.mcneel.com/yak/packages/Synapse-0.2.0-rh7_0-any.yak"},{"filename":"Synapse-0.2.0-rh6_31-any.yak","platform":"any","rhinoVersion":"rh6_31","url":"https://files.mcneel.com/yak/packages/Synapse-0.2.0-rh6_31-any.yak"}],"prerelease":false}]