[{"createdAt":"2023-12-10T12:46:34Z","version":"1.0.5","distributions":[{"filename":"VoxelTools-1.0.5-rh5_1-any.yak","platform":"any","rhinoVersion":"rh5_1","url":"https://files.mcneel.com/yak/packages/VoxelTools-1.0.5-rh5_1-any.yak"}],"prerelease":false},{"createdAt":"2022-12-02T17:43:27Z","version":"1.0.3","distributions":[{"filename":"VoxelTools-1.0.3-any-any.yak","platform":"any","rhinoVersion":"any","url":"https://files.mcneel.com/yak/packages/VoxelTools-1.0.3-any-any.yak"}],"prerelease":false},{"createdAt":"2020-06-23T20:20:20Z","version":"1.0.2","distributions":[{"filename":"VoxelTools-1.0.2-any-any.yak","platform":"any","rhinoVersion":"any","url":"https://files.mcneel.com/yak/packages/VoxelTools-1.0.2-any-any.yak"}],"prerelease":false},{"createdAt":"2020-06-23T20:06:40Z","version":"1.0.1","distributions":[{"filename":"VoxelTools-1.0.1-any-any.yak","platform":"any","rhinoVersion":"any","url":"https://files.mcneel.com/yak/packages/VoxelTools-1.0.1-any-any.yak"}],"prerelease":false}]